{
  "$schema": "https://schema.management.azure.com/schemas/2019-04-01/deploymentParameters.json#",
  "contentVersion": "1.0.0.0",
  "parameters": {
    "storageAccountName": {
      "value": "[profilesStorageAccountName]"
    },
    "storageAccountKind": {
      "value": "StorageV2"
    },
    "storageAccountSku": {
      "value": "[storageAccountSku]"
    },
    "storageAccountAccessTier": {
      "value": "Hot"
    },
    "fileShares": {
      "value": [
        {
          "name": "[profilesShareName]",
          "shareQuota": "5120",
          "roleAssignments": [
            {
              "roleDefinitionIdOrName": "Storage File Data SMB Share Contributor",
              "principalIds": [
                "[principalIds]"
              ]
            }
          ]
        }
      ]
    }
  }
}